MANIFEST.in
README.md
setup.py
pydaemon/__init__.py
pydaemon.egg-info/PKG-INFO
pydaemon.egg-info/SOURCES.txt
pydaemon.egg-info/dependency_links.txt
pydaemon.egg-info/not-zip-safe
pydaemon.egg-info/top_level.txt