Metadata-Version: 1.1
Name: pydaemon
Version: 0.1
Summary: A simple class that allows to create daemon in UNIX and Linux
Home-page: http://pypi.python.org/pypi/pydaemon
Author: marazmiki
Author-email: marazmiki@gmail.com
License: MIT license
Download-URL: https://github.com/marazmiki/pydaemon/zipball/master
Platform: UNKNOWN
Classifier: Intended Audience :: Developers
Classifier: Programming Language :: Python
Classifier: Operating System :: POSIX
Classifier: Operating System :: Unix
Classifier: Topic :: Software Development :: Libraries :: Python Modules
